flirtlines/__init__.py
flirtlines/lines.py
flirtlines_rk-1.0.0.dist-info/LICENSE
flirtlines_rk-1.0.0.dist-info/METADATA
flirtlines_rk-1.0.0.dist-info/WHEEL
flirtlines_rk-1.0.0.dist-info/top_level.txt
flirtlines_rk-1.0.0.dist-info/RECORD
