Metadata-Version: 2.2
Name: flirtlines-rk
Version: 1.0.0
Summary: A Python package that gives random flirty lines.
Home-page: https://github.com/yourusername/flirtlines
Author: raayan
Author-email: your.email@example.com
Classifier: Programming Language :: Python :: 3
Classifier: License :: OSI Approved :: MIT License
Classifier: Operating System :: OS Independent
Requires-Python: >=3.6
License-File: LICENSE
Dynamic: author
Dynamic: author-email
Dynamic: classifier
Dynamic: description
Dynamic: description-content-type
Dynamic: home-page
Dynamic: requires-python
Dynamic: summary
